.vimrc
ChangeLog
LICENSE
MANIFEST.in
README.md
README.rst
setup.py
VirtualEnvOnDemand/CreateEnv.py
VirtualEnvOnDemand/GlobalEnv.py
VirtualEnvOnDemand/InstallPackages.py
VirtualEnvOnDemand/PersistentEnv.py
VirtualEnvOnDemand/VirtualEnvInfo.py
VirtualEnvOnDemand/__init__.py
VirtualEnvOnDemand/exceptions.py
VirtualEnvOnDemand/utils.py
VirtualEnvOnDemand.egg-info/PKG-INFO
VirtualEnvOnDemand.egg-info/SOURCES.txt
VirtualEnvOnDemand.egg-info/dependency_links.txt
VirtualEnvOnDemand.egg-info/requires.txt
VirtualEnvOnDemand.egg-info/top_level.txt
doc/VirtualEnvOnDemand.CreateEnv.html
doc/VirtualEnvOnDemand.GlobalEnv.html
doc/VirtualEnvOnDemand.InstallPackages.html
doc/VirtualEnvOnDemand.PersistentEnv.html
doc/VirtualEnvOnDemand.VirtualEnvInfo.html
doc/VirtualEnvOnDemand.exceptions.html
doc/VirtualEnvOnDemand.html
doc/VirtualEnvOnDemand.utils.html
doc/exceptions.html
doc/index.html
examples/on_demand.py
examples/persistent_venv_old.py
examples/use_venv.py
examples/venv.py
examples/VirtualEnvOnDemand/CreateEnv.py
examples/VirtualEnvOnDemand/GlobalEnv.py
examples/VirtualEnvOnDemand/InstallPackages.py
examples/VirtualEnvOnDemand/PersistentEnv.py
examples/VirtualEnvOnDemand/VirtualEnvInfo.py
examples/VirtualEnvOnDemand/__init__.py
examples/VirtualEnvOnDemand/exceptions.py
examples/VirtualEnvOnDemand/utils.py