Metadata-Version: 1.1
Name: VirtualEnvOnDemand
Version: 6.0.0
Summary: Easily create and use virtualenvs and provides the ability for an application to install and use its runtime dependencies at import time
Home-page: https://github.com/kata198/VirtualEnvOnDemand
Author: Tim Savannah
Author-email: kata198@gmail.com
License: LGPLv3
Keywords: virtualenv,on,demand,pip,install,import,runtime,ImportError,reload,module,package
Platform: UNKNOWN
Classifier: Development Status :: 5 - Production/Stable
Classifier: Programming Language :: Python
Classifier: License :: OSI Approved :: GNU Lesser General Public License v3 (LGPLv3)
Classifier: Programming Language :: Python :: 2
Classifier: Programming Language :: Python :: 2
Classifier: Programming Language :: Python :: 2.7
Classifier: Programming Language :: Python :: 3
Classifier: Programming Language :: Python :: 3.3
Classifier: Programming Language :: Python :: 3.4
Classifier: Programming Language :: Python :: 3.5
Classifier: Programming Language :: Python :: 3.6
Classifier: Topic :: System :: Installation/Setup
Classifier: Topic :: Software Development :: Libraries :: Python Modules
Classifier: Operating System :: Microsoft :: Windows
Classifier: Operating System :: POSIX
Classifier: Operating System :: Unix
Classifier: Operating System :: MacOS
Classifier: Operating System :: OS Independent
Requires: virtualenv
